{
  "report_timestamp": "2025-09-20T14:25:42.412048",
  "empire_uptime_hours": 5.411111111111111e-07,
  "total_capital": 500000.0,
  "empire_metrics": {
    "total_signals_generated": 0,
    "total_orders_executed": 0,
    "total_profit_loss": 0.0,
    "risk_overrides_triggered": 0,
    "rebalances_executed": 0,
    "uptime_hours": 5.411111111111111e-07
  },
  "trading_performance": {
    "autonomous_active": false,
    "trading_enabled": true,
    "risk_override_active": false,
    "market_regime": "VOLATILE",
    "signals_generated": 36,
    "orders_executed": 28,
    "active_signals": 34,
    "runtime": "0:00:30.004787",
    "latest_symbols_tracked": 34
  },
  "risk_management": {
    "monitoring_active": false,
    "total_alerts": 0,
    "active_overrides": 0,
    "critical_alerts": 0,
    "recent_alerts": 0,
    "override_history": 0,
    "emergency_notifications_configured": 2
  },
  "capital_allocation": {
    "total_capital": 500000.0,
    "total_allocated": 0.0,
    "available_capital": 500000.0,
    "emergency_reserve": 25000.0,
    "allocation_method": "sharpe_optimization",
    "last_rebalance": "2025-09-20T14:25:12.407369",
    "allocations": {
      "GPU_AI_AGENT": {
        "target_weight": 1.0,
        "current_weight": 0.0,
        "target_capital": 500000.0,
        "current_capital": 0.0,
        "last_rebalance": "2025-09-20T14:25:12.407969"
      },
      "GPU_PATTERN_RECOGNITION": {
        "target_weight": 0.5,
        "current_weight": 0.0,
        "target_capital": 250000.0,
        "current_capital": 0.0,
        "last_rebalance": "2025-09-20T14:25:12.408013"
      },
      "GPU_MOMENTUM_SCANNER": {
        "target_weight": 0.3333333333333333,
        "current_weight": 0.0,
        "target_capital": 166666.66666666666,
        "current_capital": 0.0,
        "last_rebalance": "2025-09-20T14:25:12.408051"
      },
      "GPU_OPTIONS_ENGINE": {
        "target_weight": 0.25,
        "current_weight": 0.0,
        "target_capital": 125000.0,
        "current_capital": 0.0,
        "last_rebalance": "2025-09-20T14:25:12.408085"
      },
      "RD_ENHANCED_SIGNALS": {
        "target_weight": 0.2,
        "current_weight": 0.0,
        "target_capital": 100000.0,
        "current_capital": 0.0,
        "last_rebalance": "2025-09-20T14:25:12.408116"
      }
    },
    "portfolio_value": 0.0,
    "total_rebalances": 0
  },
  "monitoring_status": {
    "monitoring_active": false,
    "components_monitored": 9,
    "total_alerts": 0,
    "recent_alerts": 0,
    "performance_records": 1,
    "dashboard_last_updated": "2025-09-20T14:25:12.411434",
    "system_health_summary": {
      "trading_orchestrator": {
        "status": "ONLINE",
        "last_update": "2025-09-20T14:25:12.408162"
      },
      "risk_system": {
        "status": "ONLINE",
        "last_update": "2025-09-20T14:25:12.408181"
      },
      "capital_allocator": {
        "status": "ONLINE",
        "last_update": "2025-09-20T14:25:12.408198"
      },
      "market_data_engine": {
        "status": "ONLINE",
        "last_update": "2025-09-20T14:25:12.408632"
      },
      "execution_engine": {
        "status": "ONLINE",
        "last_update": "2025-09-20T14:25:12.408652"
      },
      "risk_override_system": {
        "status": "ONLINE",
        "last_update": "2025-09-20T14:25:12.408671"
      },
      "capital_allocation_engine": {
        "status": "ONLINE",
        "last_update": "2025-09-20T14:25:12.408733"
      },
      "gpu_trading_systems": {
        "status": "ONLINE",
        "last_update": "2025-09-20T14:25:12.408785"
      },
      "autonomous_orchestrator": {
        "status": "ONLINE",
        "last_update": "2025-09-20T14:25:12.410164"
      }
    }
  }
}