{
  "cycle": 31,
  "timestamp": "2025-09-19T12:36:53.084074",
  "total_opportunities": 50,
  "total_strategies": 25,
  "top_opportunities": [
    {
      "ticker": "NTLA",
      "price": 15.550000190734863,
      "market_cap": 1669244160,
      "avg_volume": 4788539,
      "momentum_5d": 0.34399313750121174,
      "implied_volatility": 1.2398033485243056,
      "options_available": true,
      "discovery_time": "2025-09-19T12:36:36.790163",
      "score": 104.788539,
      "dte": 27
    },
    {
      "ticker": "INTC",
      "price": 29.63680076599121,
      "market_cap": 138402742272,
      "avg_volume": 103852538,
      "momentum_5d": 0.19647962124692397,
      "implied_volatility": 0.6424929111480713,
      "options_available": true,
      "discovery_time": "2025-09-19T12:36:31.367120",
      "score": 103.89725323949952,
      "dte": 13
    },
    {
      "ticker": "SNAP",
      "price": 8.085000038146973,
      "market_cap": 13662296064,
      "avg_volume": 61264044,
      "momentum_5d": 0.0837801604294961,
      "implied_volatility": 1.2000441221217106,
      "options_available": true,
      "discovery_time": "2025-09-19T12:36:27.442751",
      "score": 98.37801604294961,
      "dte": 13
    },
    {
      "ticker": "HOOD",
      "price": 123.43000030517578,
      "market_cap": 109689167872,
      "avg_volume": 45667096,
      "momentum_5d": 0.07489330607844069,
      "implied_volatility": 0.754955939437624,
      "options_available": true,
      "discovery_time": "2025-09-19T12:36:17.185229",
      "score": 97.48933060784407,
      "dte": 13
    },
    {
      "ticker": "RIVN",
      "price": 14.324999809265137,
      "market_cap": 17382440960,
      "avg_volume": 40433188,
      "momentum_5d": 0.05330877996027383,
      "implied_volatility": 0.6876901590401785,
      "options_available": true,
      "discovery_time": "2025-09-19T12:36:13.280325",
      "score": 94.09989390004523,
      "dte": 13
    },
    {
      "ticker": "RIVN",
      "price": 14.324999809265137,
      "market_cap": 17382440960,
      "avg_volume": 40433188,
      "momentum_5d": 0.05330877996027383,
      "implied_volatility": 0.6876901590401785,
      "options_available": true,
      "discovery_time": "2025-09-19T12:36:33.408065",
      "score": 94.09989390004523,
      "dte": 13
    },
    {
      "ticker": "TSLA",
      "price": 425.864990234375,
      "market_cap": 1416065449984,
      "avg_volume": 91983623,
      "momentum_5d": 0.03859375026746781,
      "implied_volatility": 0.7026332929021661,
      "options_available": true,
      "discovery_time": "2025-09-19T12:36:14.116486",
      "score": 93.85937502674678,
      "dte": 13
    },
    {
      "ticker": "TSLA",
      "price": 425.7049865722656,
      "market_cap": 1415533297664,
      "avg_volume": 91983623,
      "momentum_5d": 0.03820353551091982,
      "implied_volatility": 0.7239644497323965,
      "options_available": true,
      "discovery_time": "2025-09-19T12:36:22.632200",
      "score": 93.82035355109198,
      "dte": 13
    },
    {
      "ticker": "GRAB",
      "price": 6.365600109100342,
      "market_cap": 25949782016,
      "avg_volume": 40995350,
      "momentum_5d": 0.03674271132254514,
      "implied_volatility": 0.912601083984375,
      "options_available": true,
      "discovery_time": "2025-09-19T12:36:42.529823",
      "score": 93.67427113225452,
      "dte": 13
    },
    {
      "ticker": "AMD",
      "price": 156.69129943847656,
      "market_cap": 254285479936,
      "avg_volume": 56386834,
      "momentum_5d": -0.027728370079973197,
      "implied_volatility": 0.7422536785388383,
      "options_available": true,
      "discovery_time": "2025-09-19T12:36:18.846366",
      "score": 92.77283700799732,
      "dte": 13
    }
  ],
  "best_strategies": [
    {
      "strategy": "covered_call",
      "ticker": "AMC",
      "stock_price": 2.990000009536743,
      "strike": 4.5,
      "premium": 0.06,
      "dte": 13,
      "expected_return": 14.742732047628488,
      "allocation_required": 2.990000009536743,
      "max_profit": 1.569999990463257,
      "opportunity_score": 84.41697521412536,
      "implied_volatility": 2.613934801432292
    },
    {
      "strategy": "covered_call",
      "ticker": "AMC",
      "stock_price": 2.990000009536743,
      "strike": 4.0,
      "premium": 0.08,
      "dte": 13,
      "expected_return": 10.235399929254639,
      "allocation_required": 2.990000009536743,
      "max_profit": 1.089999990463257,
      "opportunity_score": 84.41697521412536,
      "implied_volatility": 2.613934801432292
    },
    {
      "strategy": "covered_call",
      "ticker": "NTLA",
      "stock_price": 15.550000190734863,
      "strike": 22.5,
      "premium": 0.25,
      "dte": 27,
      "expected_return": 6.259378106816651,
      "allocation_required": 15.550000190734863,
      "max_profit": 7.199999809265137,
      "opportunity_score": 104.788539,
      "implied_volatility": 1.2398033485243056
    },
    {
      "strategy": "covered_call",
      "ticker": "AMC",
      "stock_price": 2.990000009536743,
      "strike": 3.5,
      "premium": 0.11,
      "dte": 13,
      "expected_return": 5.821970563346912,
      "allocation_required": 2.990000009536743,
      "max_profit": 0.6199999904632568,
      "opportunity_score": 84.41697521412536,
      "implied_volatility": 2.613934801432292
    },
    {
      "strategy": "covered_call",
      "ticker": "SNAP",
      "stock_price": 8.085000038146973,
      "strike": 9.5,
      "premium": 0.07,
      "dte": 13,
      "expected_return": 5.1569857144660185,
      "allocation_required": 8.085000038146973,
      "max_profit": 1.4849999618530274,
      "opportunity_score": 98.37801604294961,
      "implied_volatility": 1.2000441221217106
    },
    {
      "strategy": "covered_call",
      "ticker": "NIO",
      "stock_price": 7.375,
      "strike": 8.5,
      "premium": 0.21,
      "dte": 13,
      "expected_return": 5.082398956975228,
      "allocation_required": 7.375,
      "max_profit": 1.335,
      "opportunity_score": 92.45856176288362,
      "implied_volatility": 0.5882219411892361
    },
    {
      "strategy": "covered_call",
      "ticker": "FOLD",
      "stock_price": 8.364999771118164,
      "strike": 11.0,
      "premium": 0.35,
      "dte": 27,
      "expected_return": 4.8240026271425815,
      "allocation_required": 8.364999771118164,
      "max_profit": 2.985000228881836,
      "opportunity_score": 82.75345950812212,
      "implied_volatility": 1.931643989013672
    },
    {
      "strategy": "covered_call",
      "ticker": "BBBY",
      "stock_price": 9.364999771118164,
      "strike": 10.5,
      "premium": 0.35,
      "dte": 13,
      "expected_return": 4.452134352860774,
      "allocation_required": 9.364999771118164,
      "max_profit": 1.485000228881836,
      "opportunity_score": 81.71973714812718,
      "implied_volatility": 1.2628704107306985
    },
    {
      "strategy": "covered_call",
      "ticker": "NTLA",
      "stock_price": 15.550000190734863,
      "strike": 20.0,
      "premium": 0.45,
      "dte": 27,
      "expected_return": 4.259854491947602,
      "allocation_required": 15.550000190734863,
      "max_profit": 4.899999809265137,
      "opportunity_score": 104.788539,
      "implied_volatility": 1.2398033485243056
    },
    {
      "strategy": "covered_call",
      "ticker": "SNAP",
      "stock_price": 8.085000038146973,
      "strike": 9.0,
      "premium": 0.12,
      "dte": 13,
      "expected_return": 3.5942627305449015,
      "allocation_required": 8.085000038146973,
      "max_profit": 1.0349999618530275,
      "opportunity_score": 98.37801604294961,
      "implied_volatility": 1.2000441221217106
    }
  ],
  "discovery_stats": {
    "avg_iv": 0.6797708579939709,
    "avg_score": 72.75871580588526,
    "avg_return": 4.239302852617226,
    "best_return": 14.742732047628488
  }
}